{
    "001": [
        {
            "name_group": "group1",
            "profile": "unknow.jpg"
        },
        {
            "name_group": "group2",
            "profile": "unknow.jpg"
        },
        {
            "name_group": "hello1",
            "profile": "unknow.jpg"
        },
        {
            "profile": "unknow.jpg",
            "name_group": "newgroup"
        },
        {
            "name_group": "hello"
        }
    ],
    "002": [
        {
            "name_group": "group1",
            "profile": "unknow.jpg"
        },
        {
            "name_group": "newgroup",
            "profile": "unknow.jpg"
        },
        {
            "profile": "unknow.jpg",
            "name_group": "newgroup"
        },
        {
            "name_group": "hello"
        }
    ],
    "003": [
        {
            "name_group": "group1",
            "profile": "unknow.jpg"
        }
    ],
    "004": [
        {
            "name_group": "group1",
            "profile": "unknow.jpg"
        },
        {
            "name_group": 0
        }
    ],
    "newgroup": null,
    "Create Group Chat": null,
    "": null,
    "unknow.jpg": null
}